TDSR_Support/TDSR_AmBit_GUI.py
TDSR_Support/TDSR_logging.py
TDSR_Support/TDSR_radioAPI.py
TDSR_Support/TDSR_radioConnection.py
TDSR_Support/TDSR_radioControl.py
TDSR_Support/TDSR_settings.py
TDSR_Support/__init__.py
TDSR_Support/crc16.py
TDSR_Support/logReader.py
TDSR_Support/logReader_Minimal.py
TDSR_Support/JsonDoc/.DS_Store
TDSR_Support/JsonDoc/.txt
TDSR_Support/JsonDoc/API.md
TDSR_Support/JsonDoc/API.template.md
TDSR_Support/JsonDoc/APIwith_cat_template.md
TDSR_Support/JsonDoc/DATA_CONFIRM.txt
TDSR_Support/JsonDoc/DATA_INFO.txt
TDSR_Support/JsonDoc/DATA_REQUEST.txt
TDSR_Support/JsonDoc/NETWORKING_GET_SLOT_MAP_CONFIRM.txt
TDSR_Support/JsonDoc/NETWORKING_GET_SLOT_MAP_REQUEST.txt
TDSR_Support/JsonDoc/NETWORKING_GET_STATS_CONFIRM.txt
TDSR_Support/JsonDoc/NETWORKING_GET_STATS_REQUEST.txt
TDSR_Support/JsonDoc/NETWORKING_SET_SLOT_MAP_CONFIRM.txt
TDSR_Support/JsonDoc/NETWORKING_SET_SLOT_MAP_REQUEST.txt
TDSR_Support/JsonDoc/NET_DATA_QUEUE_STATUS_CONFIRM.txt
TDSR_Support/JsonDoc/NET_DATA_QUEUE_STATUS_REQUEST.txt
TDSR_Support/JsonDoc/RADIO_APPLY_PRESET_CONFIRM.txt
TDSR_Support/JsonDoc/RADIO_APPLY_PRESET_REQUEST.txt
TDSR_Support/JsonDoc/RADIO_DELETE_PRESET_CONFIRM.txt
TDSR_Support/JsonDoc/RADIO_DELETE_PRESET_REQUEST.txt
TDSR_Support/JsonDoc/RADIO_GET_ACTIVE_PRESET_CONFIRM.txt
TDSR_Support/JsonDoc/RADIO_GET_ACTIVE_PRESET_REQUEST.txt
TDSR_Support/JsonDoc/RADIO_GET_CONFIG_CONFIRM.txt
TDSR_Support/JsonDoc/RADIO_GET_CONFIG_REQUEST.txt
TDSR_Support/JsonDoc/RADIO_GET_CONNECT_REQUEST.txt
TDSR_Support/JsonDoc/RADIO_GET_INFO_CONFIRM.txt
TDSR_Support/JsonDoc/RADIO_GET_INFO_REQUEST.txt
TDSR_Support/JsonDoc/RADIO_GET_IP_CONFIRM.txt
TDSR_Support/JsonDoc/RADIO_GET_IP_REQUEST.txt
TDSR_Support/JsonDoc/RADIO_GET_NODE_CONFIG_CONFIRM.txt
TDSR_Support/JsonDoc/RADIO_GET_NODE_CONFIG_REQUEST.txt
TDSR_Support/JsonDoc/RADIO_GET_PRESET_CONFIRM.txt
TDSR_Support/JsonDoc/RADIO_GET_PRESET_REQUEST.txt
TDSR_Support/JsonDoc/RADIO_GET_STATE_CONFIRM.txt
TDSR_Support/JsonDoc/RADIO_GET_STATE_REQUEST.txt
TDSR_UWB-1.549.dist-info/LICENSE.txt
TDSR_UWB-1.549.dist-info/METADATA
TDSR_UWB-1.549.dist-info/WHEEL
TDSR_UWB-1.549.dist-info/top_level.txt
TDSR_UWB-1.549.dist-info/RECORD
